tests/__init__.py
tests/conftest.py
tests/test_events.py
tests/test_handshake.py
tests/test_injection_server.py
tests/test_mcp_protocol.py
tests/test_server_integration.py
tests/test_uri_handling.py
tests/test_zed_mode.py
orange_mcp_server_llmling-0.5.8.dist-info/METADATA
orange_mcp_server_llmling-0.5.8.dist-info/WHEEL
orange_mcp_server_llmling-0.5.8.dist-info/entry_points.txt
orange_mcp_server_llmling-0.5.8.dist-info/licenses/LICENSE
orange_mcp_server_llmling-0.5.8.dist-info/RECORD
