Metadata-Version: 2.4
Name: orange-mcp-server-llmling
Version: 0.5.8
Summary: MCP (Model context protocol) server with LLMling backend
Project-URL: Documentation, https://phil65.github.io/mcp-server-llmling/
Project-URL: Source, https://github.com/phil65/mcp-server-llmling
Project-URL: Issues, https://github.com/phil65/mcp-server-llmling/issues
Project-URL: Discussions, https://github.com/phil65/mcp-server-llmling/discussions
Project-URL: Code coverage, https://app.codecov.io/gh/phil65/mcp-server-llmling
Author-email: Philipp Temminghoff <philipptemminghoff@googlemail.com>
License: MIT License
License-File: LICENSE
Classifier: Development Status :: 4 - Beta
Classifier: Intended Audience :: Developers
Classifier: Operating System :: OS Independent
Classifier: Programming Language :: Python :: 3
Classifier: Programming Language :: Python :: 3 :: Only
Classifier: Programming Language :: Python :: 3.12
Classifier: Programming Language :: Python :: 3.13
Classifier: Programming Language :: Python :: 3.14
Classifier: Topic :: Documentation
Classifier: Topic :: Software Development
Classifier: Topic :: Utilities
Classifier: Typing :: Typed
Requires-Python: >=3.12
Requires-Dist: fastapi[standard]>=0.115.6
Requires-Dist: llmling>=1.0.0
Requires-Dist: logfire>=2.6.2
Requires-Dist: mcp>=1.1.0
Requires-Dist: pydantic
Requires-Dist: universal-pathlib>=0.2.5
Requires-Dist: upathtools[httpx]
Requires-Dist: uvicorn
Requires-Dist: websockets>=14.1
Provides-Extra: gui
Requires-Dist: nicegui; extra == 'gui'
